survey_factory/__init__.py
survey_factory/generate_survey.py
survey_factory/sequence_data.py
survey_factory/survey.py
survey_factory-0.1.dist-info/LICENSE
survey_factory-0.1.dist-info/METADATA
survey_factory-0.1.dist-info/WHEEL
survey_factory-0.1.dist-info/top_level.txt
survey_factory-0.1.dist-info/RECORD
